{
    "1.webp": {
        "caption": "two women in red and yellow dresses posing for the camera",
        "tags": [
            "crop",
            "plume",
            "adult female",
            "photographic camera",
            "women",
            "coiffure",
            "television camera",
            "coiffe",
            "trim",
            "curry",
            "set",
            "tv camera",
            "dress",
            "cut back",
            "garb",
            "habilitate",
            "preen",
            "woman",
            "get dressed",
            "attire",
            "clothe",
            "arrange",
            "wearing apparel",
            "tog",
            "dress up",
            "dresses",
            "cleaning lady",
            "cleaning woman",
            "apparel",
            "camera",
            "decorate",
            "primp",
            "frock",
            "garnish",
            "garment",
            "snip",
            "womanhood",
            "enclothe",
            "coif",
            "fair sex",
            "clip",
            "do",
            "lop",
            "prune",
            "groom",
            "fit out",
            "line up",
            "charwoman",
            "raiment",
            "clothes",
            "char",
            "dress out"
        ]
    },
    "2.webp": {
        "caption": "a pair of white shoes on a blue and pink background",
        "tags": [
            "wild blue yonder",
            "juicy",
            "bluing",
            "pinko",
            "dispirited",
            "shoe",
            "blueing",
            "twain",
            "twosome",
            "brace",
            "background knowledge",
            "mate",
            "couplet",
            "geminate",
            "backcloth",
            "blue air",
            "duo",
            "ping",
            "screen background",
            "risque",
            "ground",
            "down",
            "blueness",
            "dark",
            "pinkish",
            "setting",
            "scope",
            "place",
            "couple",
            "tap",
            "profane",
            "drab",
            "blue-blooded",
            "dreary",
            "drear",
            "rap",
            "yoke",
            "racy",
            "backdrop",
            "background",
            "sorry",
            "low",
            "gloomy",
            "match",
            "pair",
            "grim",
            "amobarbital sodium",
            "dyad",
            "down in the mouth",
            "downcast",
            "blasphemous",
            "patrician",
            "shoes",
            "horseshoe",
            "aristocratical",
            "low-spirited",
            "distich",
            "blue devil",
            "pink",
            "downplay",
            "knock",
            "blue",
            "depressed",
            "spicy",
            "duad",
            "brake shoe",
            "blue angel",
            "skid",
            "play down",
            "disconsolate",
            "blueish",
            "gentle",
            "naughty",
            "twin",
            "partner off",
            "blue sky",
            "copulate",
            "span",
            "desktop",
            "duet",
            "Amytal",
            "downhearted",
            "garden pink",
            "pair off",
            "puritanic",
            "gamy",
            "gamey",
            "background signal",
            "bluish",
            "puritanical",
            "dingy",
            "dismal",
            "aristocratic"
        ]
    }
}